sdk/__init__.py
sdk/sdk.py
sdk/sdkconfiguration.py
sdk/models/__init__.py
sdk/models/errors/__init__.py
sdk/models/errors/sdkerror.py
sdk/models/operations/__init__.py
sdk/models/operations/get_benefits_enrollment_id_.py
sdk/models/operations/get_benefits_plan_enrollment.py
sdk/models/operations/get_benefits_plan_enrollment_id_.py
sdk/models/operations/get_benefits_service.py
sdk/models/operations/patch_benefits_service_id_.py
sdk/models/shared/__init__.py
sdk/models/shared/a71f30be878693b235f8c5f1650be03c9920ca9821526545760476436104c9dc.py
sdk/models/shared/e974d9e9e5676123cf56d2fd858ece1c24be8be15b96a100963b7cb1afada329.py
sdk/models/shared/enrollment.py
sdk/models/shared/planenrollment.py
sdk/models/shared/planenrollmentcoveragemonth.py
sdk/models/shared/serviceenablementresponse.py
sdk/models/shared/serviceenablementupdate.py
sdk/models/shared/userroles.py
sdk/utils/__init__.py
sdk/utils/retries.py
sdk/utils/utils.py
wingspan_notifications-1.0.0.dist-info/METADATA
wingspan_notifications-1.0.0.dist-info/WHEEL
wingspan_notifications-1.0.0.dist-info/top_level.txt
wingspan_notifications-1.0.0.dist-info/RECORD
